azure/mgmt/resourceconnector/__init__.py
azure/mgmt/resourceconnector/_configuration.py
azure/mgmt/resourceconnector/_patch.py
azure/mgmt/resourceconnector/_resource_connector_mgmt_client.py
azure/mgmt/resourceconnector/_serialization.py
azure/mgmt/resourceconnector/_vendor.py
azure/mgmt/resourceconnector/_version.py
azure/mgmt/resourceconnector/py.typed
azure/mgmt/resourceconnector/aio/__init__.py
azure/mgmt/resourceconnector/aio/_configuration.py
azure/mgmt/resourceconnector/aio/_patch.py
azure/mgmt/resourceconnector/aio/_resource_connector_mgmt_client.py
azure/mgmt/resourceconnector/aio/operations/__init__.py
azure/mgmt/resourceconnector/aio/operations/_appliances_operations.py
azure/mgmt/resourceconnector/aio/operations/_patch.py
azure/mgmt/resourceconnector/models/__init__.py
azure/mgmt/resourceconnector/models/_models_py3.py
azure/mgmt/resourceconnector/models/_patch.py
azure/mgmt/resourceconnector/models/_resource_connector_mgmt_client_enums.py
azure/mgmt/resourceconnector/operations/__init__.py
azure/mgmt/resourceconnector/operations/_appliances_operations.py
azure/mgmt/resourceconnector/operations/_patch.py
azure_mgmt_resourceconnector-1.0.0.dist-info/LICENSE
azure_mgmt_resourceconnector-1.0.0.dist-info/LICENSE.txt
azure_mgmt_resourceconnector-1.0.0.dist-info/METADATA
azure_mgmt_resourceconnector-1.0.0.dist-info/WHEEL
azure_mgmt_resourceconnector-1.0.0.dist-info/top_level.txt
azure_mgmt_resourceconnector-1.0.0.dist-info/RECORD
